{
  "file_path": "investigations/telus_cpk_land_investigation/analysis/DAMIAN_CRITICAL_REVIEW.md",
  "document_type": "team_documentation",
  "title": "\ud83c\udfad CRITICAL REVIEW: Robert Telus Investigation - Devil's Advocate Analysis",
  "detected_at": "2025-11-04T19:22:45.019266",
  "processing_mode": "realtime",
  "priority": "immediate",
  "content_preview": "# \ud83c\udfad CRITICAL REVIEW: Robert Telus Investigation - Devil's Advocate Analysis\n\n**Prepared by:** Damian Rousseau (Critical Thinking Agent)  \n**Experience Level:** Intermediate (150 XP)  \n**Date:** 2025-11-04  \n**Investigation ID:** INV-2025-11-04-001  \n**Reviewed:** Elena (OSINT) + Marcus (Financial) + Adrian (Legal) + Maya (Data)  \n**Status:** Phase 5 Complete - Critical Review with Source Verification  \n\n---\n\n## \ud83c\udfaf MY ROLE\n\nI am the **Devil's Advocate**. My job is NOT to be negative - my job is to"
}